pycap2low
